seq2seqdistill/distill.py
seq2seqdistill/main.py
seq2seqdistill/seq2seq_distill_trainer.py
seq2seqdistill/utils.py
seq2seqdistill-0.1.7.dist-info/LICENSE
seq2seqdistill-0.1.7.dist-info/METADATA
seq2seqdistill-0.1.7.dist-info/WHEEL
seq2seqdistill-0.1.7.dist-info/top_level.txt
seq2seqdistill-0.1.7.dist-info/RECORD
