Metadata-Version: 2.1
Name: seq2seqdistill
Version: 0.1.7
License-File: LICENSE
